karrio/server/pricing/__init__.py
karrio/server/pricing/admin.py
karrio/server/pricing/apps.py
karrio/server/pricing/models.py
karrio/server/pricing/serializers.py
karrio/server/pricing/signals.py
karrio/server/pricing/tests.py
karrio/server/pricing/views.py
karrio/server/pricing/migrations/0001_initial.py
karrio/server/pricing/migrations/0002_auto_20201127_0721.py
karrio/server/pricing/migrations/0003_auto_20201230_0820.py
karrio/server/pricing/migrations/0004_auto_20201231_1402.py
karrio/server/pricing/migrations/0005_auto_20210204_1725.py
karrio/server/pricing/migrations/0006_auto_20210217_1109.py
karrio/server/pricing/migrations/0007_auto_20210218_1202.py
karrio/server/pricing/migrations/0008_auto_20210418_0504.py
karrio/server/pricing/migrations/0009_auto_20210603_2149.py
karrio/server/pricing/migrations/0010_auto_20210612_1608.py
karrio/server/pricing/migrations/0011_auto_20210615_1601.py
karrio/server/pricing/migrations/0012_surcharge_carrier_accounts.py
karrio/server/pricing/migrations/0013_alter_surcharge_services.py
karrio/server/pricing/migrations/0014_auto_20211013_1520.py
karrio/server/pricing/migrations/0015_auto_20211204_1350.py
karrio/server/pricing/migrations/0016_auto_20211220_1500.py
karrio/server/pricing/migrations/0017_alter_surcharge_services.py
karrio/server/pricing/migrations/0018_alter_surcharge_services.py
karrio/server/pricing/migrations/0019_alter_surcharge_services.py
karrio/server/pricing/migrations/0020_auto_20220412_1215.py
karrio/server/pricing/migrations/0021_auto_20220413_0959.py
karrio/server/pricing/migrations/0022_alter_surcharge_services.py
karrio/server/pricing/migrations/0023_auto_20220504_1335.py
karrio/server/pricing/migrations/0024_auto_20220808_0803.py
karrio/server/pricing/migrations/0025_alter_surcharge_carriers.py
karrio/server/pricing/migrations/0026_auto_20220828_0158.py
karrio/server/pricing/migrations/0027_alter_surcharge_services.py
karrio_server_pricing-2026.1.4.dist-info/METADATA
karrio_server_pricing-2026.1.4.dist-info/WHEEL
karrio_server_pricing-2026.1.4.dist-info/top_level.txt
karrio_server_pricing-2026.1.4.dist-info/RECORD
